hari_cal.py
hari_cal-0.0.6.dist-info/METADATA
hari_cal-0.0.6.dist-info/WHEEL
hari_cal-0.0.6.dist-info/top_level.txt
hari_cal-0.0.6.dist-info/RECORD
