Metadata-Version: 2.1
Name: hari-cal
Version: 0.0.6
Summary: Basic math
Author: Phani Siginamsetty
License: UNKNOWN
Keywords: Oerations_in_math
Platform: UNKNOWN
Classifier: Programming Language :: Python :: 3
Classifier: License :: OSI Approved :: MIT License
Classifier: Operating System :: OS Independent
Requires-Python: >=3.6
Requires-Dist: pandas
